pycsbinarywriter/__init__.py
pycsbinarywriter/consts.py
pycsbinarywriter/csharpserializable.py
pycsbinarywriter/cstypes/__init__.py
pycsbinarywriter/cstypes/cstype.py
pycsbinarywriter/cstypes/decimal.py
pycsbinarywriter/cstypes/seven_bit_int.py
pycsbinarywriter/cstypes/simple.py
pycsbinarywriter/cstypes/strings.py
pycsbinarywriter/test/__init__.py
pycsbinarywriter/test/int7_regressions.py
pycsbinarywriter/test/simple.py
pycsbinarywriter/test/strings.py
pycsbinarywriter-0.1.2.dist-info/LICENSE
pycsbinarywriter-0.1.2.dist-info/METADATA
pycsbinarywriter-0.1.2.dist-info/WHEEL
pycsbinarywriter-0.1.2.dist-info/RECORD
