Metadata-Version: 2.1
Name: pycsbinarywriter
Version: 0.1.2
Summary: Helpers for parsing and writing binary data created by dotnet System.IO.BinaryWriters.
Home-page: https://gitlab.com/N3X15/pycsbinarywriter
License: MIT
Author: Rob Nelson
Author-email: nexisentertainment@gmail.com
Requires-Python: >=3.10,<4.0
Classifier: License :: OSI Approved :: MIT License
Classifier: Programming Language :: Python :: 3
Classifier: Programming Language :: Python :: 3.10
Classifier: Programming Language :: Python :: 3.11
Requires-Dist: pytz (>=2024.1,<2025.0)
Project-URL: Repository, https://gitlab.com/N3X15/pycsbinarywriter
